jsonthat/__init__.py
jsonthat/main.py
jsonthat/version.py
jsonthat-0.4.0.dist-info/METADATA
jsonthat-0.4.0.dist-info/WHEEL
jsonthat-0.4.0.dist-info/entry_points.txt
jsonthat-0.4.0.dist-info/RECORD
