Metadata-Version: 2.3
Name: jsonthat
Version: 0.4.0
Summary: Transform plain text to JSON
Author: Yanael Barbier
Author-email: st3w4r@gmail.com
Requires-Python: >=3.12,<4.0
Classifier: Programming Language :: Python :: 3
Classifier: Programming Language :: Python :: 3.12
Classifier: Programming Language :: Python :: 3.13
Requires-Dist: pyyaml (>=6.0.1,<7.0.0)
Requires-Dist: requests (>=2.32.3,<3.0.0)
Project-URL: Homepage, https://jsonthat.com/
Project-URL: Repository, https://github.com/st3w4r/json-that
